{"nts_statement_type":[{"value":"Nuclear Threat Statement","count":356},{"value":"Nuclear Stability Statement","count":1}],"nts_threat_type":[{"value":"Explicit Threat","count":173},{"value":"Implicit Threat","count":169},{"value":"Veiled Threat","count":14},{"value":"Overt Threat","count":1}],"capability":[{"value":"Strategic","count":305},{"value":"Tactical","count":52}],"delivery_system":[{"value":"Other","count":245},{"value":"Missile","count":101},{"value":"Aircraft","count":9},{"value":"Artillery Shell","count":2}],"conditionality":[{"value":"Conditional (Level 1)","count":294},{"value":"Implicit Condition (Level 3)","count":37},{"value":"Situational (Level 2)","count":15},{"value":"Unconditional (Level 4)","count":11}],"purpose":[{"value":"Deterrence","count":290},{"value":"Coercion","count":59},{"value":"Defense","count":8}],"tone":[{"value":"Aggressive (Level 3)","count":185},{"value":"Firm (Level 2)","count":126},{"value":"Belligerent (Level 4)","count":45},{"value":"Apocalyptic (Level 5)","count":1}],"context":[{"value":"Bilateral","count":140},{"value":"Regional Conflict","count":97},{"value":"Multilateral","count":95},{"value":"Global","count":25}],"geographical_reach":[{"value":"Regional","count":195},{"value":"Global","count":155},{"value":"Unspecified","count":7}],"consequences":[{"value":"Significant (Level 3)","count":129},{"value":"Catastrophic (Level 5)","count":122},{"value":"Severe (Level 4)","count":106}],"timeline":[{"value":"Future/Conditional","count":339},{"value":"Immediate","count":17},{"value":"Long-term","count":1}],"arms_control_and_testing":[{"value":"Withdrawal from Arms Control Agreements","count":62},{"value":"Conducting Nuclear Testing","count":25}],"audience":[{"value":"International","count":265},{"value":"Specific Group","count":87},{"value":"Domestic","count":4},{"value":"Global Community","count":1}],"specificity":[{"value":"General (Level 2)","count":151},{"value":"Specific (Level 3)","count":115},{"value":"Vague (Level 1)","count":86},{"value":"Detailed (Level 4)","count":4},{"value":"Explicit (Level 5)","count":1}],"rhetorical_device":[{"value":"Literal","count":341},{"value":"Hyperbolic","count":8},{"value":"Metaphorical","count":8}]}